{
  "hash": "7d04281a",
  "configHash": "e654e0e9",
  "lockfileHash": "b30e5ba0",
  "browserHash": "8fb20aff",
  "optimized": {
    "react": {
      "src": "../../node_modules/react/index.js",
      "file": "react.js",
      "fileHash": "e262477b",
      "needsInterop": true
    },
    "react-dom/client": {
      "src": "../../node_modules/react-dom/client.js",
      "file": "react-dom_client.js",
      "fileHash": "a70c4e9b",
      "needsInterop": true
    },
    "react-router-dom": {
      "src": "../../node_modules/react-router-dom/dist/index.js",
      "file": "react-router-dom.js",
      "fileHash": "420c406e",
      "needsInterop": false
    },
    "prop-types": {
      "src": "../../node_modules/prop-types/index.js",
      "file": "prop-types.js",
      "fileHash": "662436bd",
      "needsInterop": true
    }
  },
  "chunks": {
    "chunk-HCGKX5ED": {
      "file": "chunk-HCGKX5ED.js"
    },
    "chunk-WNPTCGAH": {
      "file": "chunk-WNPTCGAH.js"
    },
    "chunk-5WRI5ZAA": {
      "file": "chunk-5WRI5ZAA.js"
    }
  }
}